homeassistant_satellite/VERSION
homeassistant_satellite/__init__.py
homeassistant_satellite/__main__.py
homeassistant_satellite/mic.py
homeassistant_satellite/py.typed
homeassistant_satellite/remote.py
homeassistant_satellite/snd.py
homeassistant_satellite/state.py
homeassistant_satellite/util.py
homeassistant_satellite/vad.py
homeassistant_satellite/models/silero_vad.onnx
homeassistant_satellite-1.1.0.dist-info/LICENSE.md
homeassistant_satellite-1.1.0.dist-info/METADATA
homeassistant_satellite-1.1.0.dist-info/WHEEL
homeassistant_satellite-1.1.0.dist-info/top_level.txt
homeassistant_satellite-1.1.0.dist-info/RECORD
