Metadata-Version: 2.1
Name: homeassistant-satellite
Version: 1.1.0
Summary: Voice satellite for Home Assistant
Home-page: http://github.com/synesthesiam/homeassistant-satellite
Author: Michael Hansen
Author-email: mike@rhasspy.org
License: MIT
Keywords: voice satellite home assistant
Classifier: Development Status :: 3 - Alpha
Classifier: Intended Audience :: Developers
Classifier: Topic :: Text Processing :: Linguistic
Classifier: License :: OSI Approved :: MIT License
Classifier: Programming Language :: Python :: 3.7
Classifier: Programming Language :: Python :: 3.8
Classifier: Programming Language :: Python :: 3.9
Classifier: Programming Language :: Python :: 3.10
Classifier: Programming Language :: Python :: 3.11
License-File: LICENSE.md
Requires-Dist: aiohttp ==3.8.4
Requires-Dist: sounddevice ==0.4.6
Requires-Dist: numpy <2
Requires-Dist: webrtc-noise-gain ==1.2.3
Provides-Extra: silerovad
Requires-Dist: onnxruntime <2,>=1.11.0 ; extra == 'silerovad'
